cococleaner/__init__.py
cococleaner/_nbdev.py
cococleaner/coco.py
cococleaner/core.py
cococleaner/crop_tree.py
cococleaner/json_file.py
cococleaner/json_tree.py
cococleaner/main.py
cococleaner/utils.py
cococleaner/repr/__init__.py
cococleaner/repr/jsonfile.py
cocorepr/__init__.py
cocorepr/_nbdev.py
cocorepr/cli.py
cocorepr/coco.py
cocorepr/crop_tree.py
cocorepr/json_file.py
cocorepr/json_tree.py
cocorepr/main.py
cocorepr/utils.py
cocorepr-0.1.0.dist-info/LICENSE
cocorepr-0.1.0.dist-info/METADATA
cocorepr-0.1.0.dist-info/WHEEL
cocorepr-0.1.0.dist-info/entry_points.txt
cocorepr-0.1.0.dist-info/top_level.txt
cocorepr-0.1.0.dist-info/RECORD
