Metadata-Version: 2.1
Name: cocorepr
Version: 0.1.0
Summary: COCO Dataset cleaning tool
Home-page: https://github.com/neuro-inc/cocorepr
Author: artemlops
Author-email: ajuszkowski@gmail.com
License: Apache Software License 2.0
Keywords: coco data dataset cleaning git
Platform: UNKNOWN
Classifier: Development Status :: 3 - Alpha
Classifier: Intended Audience :: Developers
Classifier: Natural Language :: English
Classifier: Programming Language :: Python :: 3.6
Classifier: Programming Language :: Python :: 3.7
Classifier: Programming Language :: Python :: 3.8
Classifier: License :: OSI Approved :: Apache Software License
Requires-Python: >=3.6
Requires-Dist: dataclasses-json (>=0.5.3)
Requires-Dist: opencv-python (>=4.5.1)
